streamlit_folium/__init__.py
streamlit_folium/frontend/build/asset-manifest.json
streamlit_folium/frontend/build/bootstrap.min.css
streamlit_folium/frontend/build/index.html
streamlit_folium/frontend/build/static/js/main.fcaced76.js
streamlit_folium/frontend/build/static/js/main.fcaced76.js.LICENSE.txt
streamlit_folium/frontend/build/static/js/main.fcaced76.js.map
streamlit_folium-0.23.2.dist-info/LICENSE
streamlit_folium-0.23.2.dist-info/METADATA
streamlit_folium-0.23.2.dist-info/WHEEL
streamlit_folium-0.23.2.dist-info/top_level.txt
streamlit_folium-0.23.2.dist-info/RECORD
