Metadata-Version: 2.1
Name: streamlit_folium
Version: 0.23.2
Summary: Render Folium objects in Streamlit
Home-page: https://github.com/randyzwitch/streamlit-folium
Author: Randy Zwitch
Author-email: rzwitch@gmail.com
Requires-Python: >=3.9
License-File: LICENSE
Requires-Dist: streamlit>=1.13.0
Requires-Dist: folium!=0.15.0,>=0.13
Requires-Dist: jinja2
Requires-Dist: branca
